README.md
setup.cfg
setup.py
poeapoe/__init__.py
poeapoe.egg-info/PKG-INFO
poeapoe.egg-info/SOURCES.txt
poeapoe.egg-info/dependency_links.txt
poeapoe.egg-info/requires.txt
poeapoe.egg-info/top_level.txt