Metadata-Version: 2.1
Name: poeapoe
Version: 0.0.1
Summary: open engineering pö-a-pö
Home-page: https://github.com/lepy/poeapoe
Author: Lepy
Author-email: lepy@mailbox.org
Maintainer: Lepy
Maintainer-email: lepy@mailbox.org
License: MIT/Apache-2.0
Keywords: open engineering
Platform: UNKNOWN
Classifier: Development Status :: 3 - Alpha
Classifier: Intended Audience :: Developers
Classifier: License :: OSI Approved :: MIT License
Classifier: Natural Language :: English
Classifier: Operating System :: OS Independent
Classifier: Programming Language :: Python :: 3.7
Classifier: Programming Language :: Python :: 3.8
Classifier: Programming Language :: Python :: 3.9
Classifier: Programming Language :: Python :: 3.10
Classifier: Programming Language :: Python :: Implementation :: CPython
Classifier: Programming Language :: Python :: Implementation :: PyPy
